[
    {
        "id": 1,
        "achievementGroup": null,
        "achievementType": "NORMAL",
        "active": false,
        "counter": null,
        "data": null,
        "description": "description",
        "displayRank": 1,
        "importanceRank": 1,
        "label": "test achievement 0",
        "level": 1,
        "name": "achievement 0",
        "progress": null,
        "segments": [
            54,
            52,
            53
        ],
        "updatedAt": 1390236382695,
        "createdAt": 1390236382695
    }
]