{
    "id": "ZYHyy52GwWCAsV9AloqLQ93z",
    "birthDate": "1972-08-07",
    "email": "Mauricio_Brekke@hotmail.com",
    "firstName": "Bernardo",
    "lastName": "Davis",
    "gender": "male",
    "status": true,
    "createdAt": "2014-01-06T08:49:39.964Z",
    "updatedAt": "2014-01-06T08:49:39.964Z",
    "idArray": [
        "ThrjE1fKMMAxP1CHcd3FN5jR",
        "7CzSlgJ3x3Fu8kFzHPZ1ens9",
        "G8u0NJrz8nLYCQgCH6I8F2KT",
        "kubNu3A1TwacVVgxzWswmZxR",
        "PAg9vmi17Mb7EL1ImUB3hn70",
        "NatYeleIu447NUjJSUJQw9BG",
        "I6cYRXSs9SAuN1O6B7CtIuEs",
        "yorGx6dmlQO4CaCWl5303BML",
        "wh9Ue7lxqHTNGdAWiNOQ3M5x",
        "CSI0ycADfVFUBvSFaPqekfqJ"
    ],
    "points": 41
}